odc/loader/__init__.py
odc/loader/_aws.py
odc/loader/_builder.py
odc/loader/_dask.py
odc/loader/_driver.py
odc/loader/_reader.py
odc/loader/_rio.py
odc/loader/_utils.py
odc/loader/_zarr.py
odc/loader/py.typed
odc/loader/test_builder.py
odc/loader/test_dask.py
odc/loader/test_driver.py
odc/loader/test_memreader.py
odc/loader/test_reader.py
odc/loader/test_types.py
odc/loader/test_utils.py
odc/loader/test_utils_aws.py
odc/loader/types.py
odc/loader/testing/__init__.py
odc/loader/testing/fixtures.py
odc_loader-0.6.0.dist-info/licenses/LICENSE
odc_loader-0.6.0.dist-info/WHEEL
odc_loader-0.6.0.dist-info/METADATA
odc_loader-0.6.0.dist-info/RECORD
